{
	"data": [
		{
			"label": "中国",
			"value": "china",
			"note": "人民币(元)",
			"children": [
				{
					"label": "2019",
					"note": "人民币(元)",
					"value": 1
				}
			]
		},
		{
			"label": "民国",
			"value": "minguo",
			"note": "银元(元)",
			"children": [
				{
					"label": "民国七年",
					"note": "银元(元)",
					"value": 1325.3
			    },
				{
					"label": "民国二十二年",
					"note": "银元(元)",
					"value": 157.14
				},
				{
					"label": "民国二十五年",
					"note": "银元(元)",
					"value": 164.77
				},
				{
					"label": "民国二十六年",
					"note": "银元(元)",
					"value": 180.68
				},
				{
					"label": "民国二十七年",
					"note": "银元(元)",
					"value": 178.93
				},
				{
					"label": "民国二十八年",
					"note": "银元(元)",
					"value": 128.73
				},
				{
					"label": "民国二十九年",
					"note": "银元(元)",
					"value": 63.22
				}
			]
		},
		{
			"label": "清",
			"value": "qing",
			"note": "白银(两)",
			"children": [
				{
					"label": "乾隆二年",
					"value": 3666.67,
					"note": "银两(两)"
				},
				{
					"label": "乾隆十六年",
					"value": 2444.44,
					"note": "银两(两)"
				},
				{
					"label": "嘉庆五年",
					"value": 1.78,
					"note": "铜钱(文)"
				},
				{
					"label": "嘉庆十七年",
					"value": 4.4,
					"note": "铜钱(文)"
				},
				{
					"label": "道光四年",
					"value": 4.89,
					"note": "铜钱(文)"
				},
				{
					"label": "道光二十二年",
					"value": 5.5,
					"note": "铜钱(文)"
				}
			]
		},
		{
			"label": "明",
			"value": "ming",
			"note": "铜钱(文)",
			"children": [
				{
					"label": "洪武年间",
					"note": "铜钱(文)",
					"value": 1.22
				},
				{
					"label": "万历三十六年",
					"note": "铜钱(文)",
					"value": 2.44
				}	
			]
		},
		{
			"label": "元",
			"value": "yuan",
			"note": "中统钞(贯)",
			"children": [
				{
					"label": "至顺元年",
					"note": "中统钞(贯)",
					"value": 110
				}
			]
		},
		{
			"label": "南宋",
			"value": "nansong",
			"note": "会子(文)",
			"children": [
				{
					"label": "绍兴年间",
					"note": "会子(文)",
					"value": 0.73
				},
				{
					"label": "隆兴年间",
					"note": "会子(文)",
					"value": 2.44
				}	
			]
		},
		{
			"label": "北宋",
			"value": "beisong",
			"note": "铜钱(文)",
			"children": [
				{
					"label": "英宗时期",
					"note": "铜钱(文)",
					"value": 0.58
				}
			]
		},
		{
			"label": "唐",
			"value": "tang",
			"note": "铜钱(文)",
			"children": [
				{
					"label": "盛唐年间",
					"note": "铜钱(文)",
					"value": 2.03
				},
				{
					"label": "宣宗年间",
					"note": "铜钱(文)",
					"value": 4.4
				}
			]
		},
		{
			"label": "东汉",
			"value": "donghan",
			"note": "五铢钱(文)",
			"children": [
				{
					"label": "汉光武帝",
					"note": "五铢钱(文)",
					"value": 2.2
				}
			]
		},
		{
			"label": "西汉",
			"value": "xihan",
			"note": "五铢钱(文)",
			"children": [
				{
					"label": "汉武帝",
					"note": "五铢钱(文)",
					"value": 1.1
				}
			]
		}
	]
}
